{
  "realm" : "thesis-management",
  "users" : [ {
    "id" : "273f82c5-2df1-41f3-86e1-361ad5639fc5",
    "createdTimestamp" : 1739488520940,
    "username" : "testuser1",
    "enabled" : true,
    "totp" : false,
    "emailVerified" : false,
    "firstName" : "alberto",
    "lastName" : "user1",
    "email": "alberto@test.de",
    "credentials" : [ ],
    "disableableCredentialTypes" : [ ],
    "requiredActions" : [ ],
    "realmRoles" : [ "default-roles-test-realm" ],
    "notBefore" : 0,
    "groups" : [ "/administrator" ],
    "attributes": { 
        "registration_complete": [true]
    }
  },
  {
    "id" : "846aca25-d633-438c-8ccd-2d8fb2364c61",
    "createdTimestamp" : 1739488520940,
    "username" : "testuser2",
    "enabled" : true,
    "totp" : false,
    "emailVerified" : false,
    "firstName" : "franz",
    "lastName" : "user2",
    "email": "franz@test.de",
    "credentials" : [ ],
    "disableableCredentialTypes" : [ ],
    "requiredActions" : [ ],
    "realmRoles" : [ "default-roles-test-realm" ],
    "notBefore" : 0,
    "groups" : [ "/student" ],
    "attributes": { 
        "registration_complete": [false],
        "registration_token": ["1234"]
    }
  },
  {
    "id" : "810f0803-2b1b-422b-8613-14d6b215664a",
    "createdTimestamp" : 1739488520940,
    "username" : "testuser3",
    "enabled" : true,
    "totp" : false,
    "emailVerified" : false,
    "firstName" : "gonk",
    "lastName" : "droid",
    "email": "gonk_droid@test.de",
    "credentials" : [ ],
    "disableableCredentialTypes" : [ ],
    "requiredActions" : [ ],
    "realmRoles" : [ "default-roles-test-realm" ],
    "notBefore" : 0,
    "groups" : [ "/supervisor" ],
    "attributes": { 
        "registration_complete": [false],
        "registration_token": ["4321"]
    }
  }]
}
